mkdocs_hr_plugin/__init__.py
mkdocs_hr_plugin/plugin.py
mkdocs_hr_plugin/assets/extra.css
mkdocs_hr_plugin/assets/extra.js
mkdocs_hr_plugin-0.1.1.dist-info/METADATA
mkdocs_hr_plugin-0.1.1.dist-info/WHEEL
mkdocs_hr_plugin-0.1.1.dist-info/entry_points.txt
mkdocs_hr_plugin-0.1.1.dist-info/top_level.txt
mkdocs_hr_plugin-0.1.1.dist-info/RECORD
