Metadata-Version: 2.4
Name: mkdocs-hr-plugin
Version: 0.1.1
Summary: A MkDocs plugin that converts text between triple dashes to HR elements
Home-page: https://github.com/Auzers/mkdocs-hr-plugin
Author: amaranth
Author-email: amaranth <amaranth2082@gmail.com>
Project-URL: Homepage, https://github.com/Auzers/mkdocs-hr-plugin
Classifier: Programming Language :: Python :: 3
Classifier: License :: OSI Approved :: MIT License
Classifier: Operating System :: OS Independent
Requires-Python: >=3.7
Requires-Dist: mkdocs>=1.0.0
Dynamic: author
Dynamic: home-page
Dynamic: requires-python
